Data_extractor_txt_to_csv/__init__.py
Data_extractor_txt_to_csv/extractor.py
Terriculum_first_package/__init__.py
Terriculum_first_package/extractor.py
your_package/__init__.py
your_package/extractor.py
Data_extractor_txt_to_csv-2.1.0.dist-info/METADATA
Data_extractor_txt_to_csv-2.1.0.dist-info/WHEEL
Data_extractor_txt_to_csv-2.1.0.dist-info/entry_points.txt
Data_extractor_txt_to_csv-2.1.0.dist-info/top_level.txt
Data_extractor_txt_to_csv-2.1.0.dist-info/RECORD
