Metadata-Version: 2.2
Name: Data_extractor_txt_to_csv
Version: 2.1.0
Summary: A Python package to extract data from TXT filenames and save it to CSV.
Home-page: https://github.com/yourusername/Data_extractor_txt_to_csv
Author: Terriculum
Author-email: your-email@example.com
Classifier: Programming Language :: Python :: 3
Classifier: License :: OSI Approved :: MIT License
Classifier: Operating System :: OS Independent
Requires-Python: >=3.6
Dynamic: author
Dynamic: author-email
Dynamic: classifier
Dynamic: description
Dynamic: description-content-type
Dynamic: home-page
Dynamic: requires-python
Dynamic: summary
